wcm/__init__.py
wcm/__main__.py
wcm/_component.py
wcm/_schema.py
wcm/_utils.py
wcm/resources/wings-component.yml
wcm/wings/__init__.py
wcm/wings/auth.py
wcm/wings/component.py
wcm/wings/data.py
wcm/wings/domain.py
wcm/wings/execution.py
wcm/wings/planner.py
wcm/wings/resource.py
wcm/wings/user.py
wcm/wings/userop.py
wcm-0.0.1.dist-info/LICENSE
wcm-0.0.1.dist-info/METADATA
wcm-0.0.1.dist-info/WHEEL
wcm-0.0.1.dist-info/entry_points.txt
wcm-0.0.1.dist-info/top_level.txt
wcm-0.0.1.dist-info/RECORD
