Metadata-Version: 2.1
Name: wcm
Version: 0.0.1
Summary: UNKNOWN
Home-page: https://github.com/mintproject/wcm
Author: Rajiv Mayani
Author-email: mayani@isi.edu
License: Apache
Platform: UNKNOWN
Classifier: License :: OSI Approved :: Apache Software License
Classifier: Development Status :: 3 - Alpha
Classifier: Programming Language :: Python
Classifier: Programming Language :: Python :: 3
Classifier: Programming Language :: Python :: 3.7
Classifier: Intended Audience :: Science/Research
Classifier: Operating System :: Unix
Requires-Python: >=3.5.0
Requires-Dist: Click (>=7.0)
Requires-Dist: PyYAML
Requires-Dist: yamlordereddictloader
Requires-Dist: jsonschema (>=3.0.0)
Requires-Dist: semver (>=2.8.1)
